main/__init__.py
main/main.py
my_sse_http_custom_param_server-0.1.1.dist-info/METADATA
my_sse_http_custom_param_server-0.1.1.dist-info/WHEEL
my_sse_http_custom_param_server-0.1.1.dist-info/entry_points.txt
my_sse_http_custom_param_server-0.1.1.dist-info/top_level.txt
my_sse_http_custom_param_server-0.1.1.dist-info/RECORD
