Metadata-Version: 2.1
Name: my-sse-http-custom-param-server
Version: 0.1.1
Summary: A custom MCP SSE HTTP Server with parameter support.
Author: MCP Demo
Author-email: 
License: MIT
Classifier: Programming Language :: Python :: 3
Classifier: License :: OSI Approved :: MIT License
Classifier: Framework :: FastAPI
Requires-Dist: fastapi==0.115.12
Requires-Dist: mcp==1.6.0
